ti_sensortag_wifi/__init__.py
ti_sensortag_wifi/ti_sensortag_wifi.py
ti_sensortag_wifi-0.0.1.dist-info/LICENSE
ti_sensortag_wifi-0.0.1.dist-info/METADATA
ti_sensortag_wifi-0.0.1.dist-info/WHEEL
ti_sensortag_wifi-0.0.1.dist-info/top_level.txt
ti_sensortag_wifi-0.0.1.dist-info/RECORD
