Metadata-Version: 2.1
Name: ti-sensortag-wifi
Version: 0.0.1
Summary: Python Library for collecting data from TI CC3200 SensorTag
Home-page: https://github.com/valkjsaaa/ti_sensortag_wifi
Author: Jackie Yang
Author-email: me@jackieyang.me
License: UNKNOWN
Platform: UNKNOWN
Classifier: Programming Language :: Python :: 3
Classifier: License :: OSI Approved :: MIT License
Classifier: Operating System :: OS Independent
